buckeye/__init__.py
buckeye/buckeye.py
buckeye/containers.py
buckeye/utterance.py
buckeye-1.3.dist-info/DESCRIPTION.rst
buckeye-1.3.dist-info/METADATA
buckeye-1.3.dist-info/RECORD
buckeye-1.3.dist-info/WHEEL
buckeye-1.3.dist-info/metadata.json
buckeye-1.3.dist-info/top_level.txt
