Metadata-Version: 2.0
Name: buckeye
Version: 1.3
Summary: Classes and iterators for the Buckeye Corpus
Home-page: https://github.com/scjs/buckeye/
Author: Scott Seyfarth
Author-email: UNKNOWN
License: MIT
Keywords: speech linguistics language conversation corpus
Platform: UNKNOWN
Classifier: Development Status :: 5 - Production/Stable
Classifier: Intended Audience :: Science/Research
Classifier: Topic :: Multimedia :: Sound/Audio :: Analysis
Classifier: Topic :: Multimedia :: Sound/Audio :: Speech
Classifier: Topic :: Scientific/Engineering
Classifier: License :: OSI Approved :: MIT License
Classifier: Natural Language :: English
Classifier: Programming Language :: Python :: 2
Classifier: Programming Language :: Python :: 2.7
Classifier: Programming Language :: Python :: 3
Classifier: Programming Language :: Python :: 3.6
